{
  "name": "customer-research",
  "description": "Know your customer before you build. Create detailed personas, analyze existing feedback for what they actually want, research the competitive landscape, and build an outreach plan to validate your assumptions.",
  "category": "business",
  "steps": [
    {
      "skill_name": "customer-persona-builder",
      "alias": "personas",
      "depends_on": [],
      "config": {},
      "phase_filter": null
    },
    {
      "skill_name": "feedback-analyzer",
      "alias": "voice-of-customer",
      "depends_on": [],
      "config": {},
      "phase_filter": null
    },
    {
      "skill_name": "competitor-teardown",
      "alias": "competition",
      "depends_on": ["personas"],
      "config": {},
      "phase_filter": null
    },
    {
      "skill_name": "cold-outreach-optimizer",
      "alias": "outreach",
      "depends_on": ["personas", "voice-of-customer"],
      "config": {},
      "phase_filter": null
    },
    {
      "skill_name": "email-writer",
      "alias": "outreach-emails",
      "depends_on": ["outreach", "personas"],
      "config": {},
      "phase_filter": null
    }
  ]
}
