{
  "name": "market-launch",
  "description": "Full market launch pipeline: research the market, tear down competitors, build entry strategy, create content plan.",
  "steps": [
    {
      "skill_name": "research-synthesizer",
      "alias": "research",
      "depends_on": [],
      "config": {},
      "phase_filter": null
    },
    {
      "skill_name": "competitor-teardown",
      "alias": "competitors",
      "depends_on": ["research"],
      "config": {},
      "phase_filter": null
    },
    {
      "skill_name": "market-entry-analyzer",
      "alias": "strategy",
      "depends_on": ["research", "competitors"],
      "config": {},
      "phase_filter": null
    },
    {
      "skill_name": "growth-content-system",
      "alias": "content",
      "depends_on": ["strategy"],
      "config": {},
      "phase_filter": null
    }
  ]
}